[{
    "display_title": "Diary of a Wimpy Kid: Rodrick Rules",
    "mpaa_rating": "PG",
    "critics_pick": 0,
    "byline": "Calum Marsh",
    "headline": "‘Diary of a Wimpy Kid: Rodrick Rules’ Review: Oh, Brother",
    "summary_short": "The beloved children’s book series receives another film installment.",
    "publication_date": "2022-12-02",
    "opening_date": "2022-12-02",
    "date_updated": "2022-12-02 08:02:03",
    "link": {
        "type": "article",
        "url": "https://www.nytimes.com/2022/12/02/movies/diary-of-a-wimpy-kid-rodrick-rules-review.html",
        "suggested_link_text": "Read the New York Times Review of Diary of a Wimpy Kid: Rodrick Rules"
    },
    "multimedia": {
        "type": "mediumThreeByTwo210",
        "src": "https://static01.nyt.com/images/2022/12/01/multimedia/01diary-of-a-wimpy-kid-1-906f/01diary-of-a-wimpy-kid-1-906f-mediumThreeByTwo440.jpg",
        "height": 140,
        "width": 210
    }
}, {
    "display_title": "The Eternal Daughter",
    "mpaa_rating": "PG-13",
    "critics_pick": 1,
    "byline": "Manohla Dargis",
    "headline": "‘The Eternal Daughter’ Review: Two Glorious Sides of Tilda Swinton",
    "summary_short": "The actress astonishes in two roles in Joanna Hogg’s haunting film set in a creaky castle in Wales.",
    "publication_date": "2022-12-01",
    "opening_date": null,
    "date_updated": "2022-12-01 20:02:03",
    "link": {
        "type": "article",
        "url": "https://www.nytimes.com/2022/12/01/movies/eternal-daughter-review-tilda-swinton.html",
        "suggested_link_text": "Read the New York Times Review of The Eternal Daughter"
    },
    "multimedia": {
        "type": "mediumThreeByTwo210",
        "src": "https://static01.nyt.com/images/2022/12/02/multimedia/02-eternal-print-1-4475/02-eternal-print-1-4475-mediumThreeByTwo440.jpg",
        "height": 140,
        "width": 210
    }
}, {
    "display_title": "Return to Seoul",
    "mpaa_rating": "R",
    "critics_pick": 1,
    "byline": "Amy Nicholson",
    "headline": "‘Return to Seoul’ Review: Found in Translation",
    "summary_short": "On a whim, a Frenchwoman goes to visit South Korea, the country of her birth, in Davy Chou’s drama.",
    "publication_date": "2022-12-01",
    "opening_date": null,
    "date_updated": "2022-12-01 17:43:22",
    "link": {
        "type": "article",
        "url": "https://www.nytimes.com/2022/12/01/movies/return-to-seoul-review.html",
        "suggested_link_text": "Read the New York Times Review of Return to Seoul"
    },
    "multimedia": {
        "type": "mediumThreeByTwo210",
        "src": "https://static01.nyt.com/images/2022/12/01/multimedia/return1/return1-mediumThreeByTwo440.jpg",
        "height": 140,
        "width": 210
    }
}, {
    "display_title": "Lowndes County and the Road to Black Power",
    "mpaa_rating": "",
    "critics_pick": 1,
    "byline": "Devika Girish",
    "headline": "‘Lowndes County and the Road to Black Power’ Review: A Movement That Changed America",
    "summary_short": "With arresting interviews and archival footage, this documentary looks back at a 1960s voting-rights campaign in Alabama that gave rise to a national movement for Black power.",
    "publication_date": "2022-12-01",
    "opening_date": null,
    "date_updated": "2022-12-01 17:35:04",
    "link": {
        "type": "article",
        "url": "https://www.nytimes.com/2022/12/01/movies/lowndes-county-and-the-road-to-black-power-review.html",
        "suggested_link_text": "Read the New York Times Review of Lowndes County and the Road to Black Power"
    },
    "multimedia": {
        "type": "mediumThreeByTwo210",
        "src": "https://static01.nyt.com/images/2022/12/02/multimedia/01lowndes-review-1-9838/01lowndes-review-1-9838-mediumThreeByTwo440.jpg",
        "height": 140,
        "width": 210
    }
}, {
    "display_title": "Tantura",
    "mpaa_rating": "",
    "critics_pick": 1,
    "byline": "Ben Kenigsberg",
    "headline": "‘Tantura’ Review: Unearthing the Past",
    "summary_short": "Revisiting a graduate thesis that caused controversy in Israel two decades ago, this documentary examines evidence of a possible massacre in 1948.",
    "publication_date": "2022-12-01",
    "opening_date": null,
    "date_updated": "2022-12-01 13:54:03",
    "link": {
        "type": "article",
        "url": "https://www.nytimes.com/2022/12/01/movies/tantura-review.html",
        "suggested_link_text": "Read the New York Times Review of Tantura"
    },
    "multimedia": {
        "type": "mediumThreeByTwo210",
        "src": "https://static01.nyt.com/images/2022/12/02/multimedia/tantura1/tantura1-1-79f8-mediumThreeByTwo440.jpg",
        "height": 140,
        "width": 210
    }
}, {
    "display_title": "Sr.",
    "mpaa_rating": "R",
    "critics_pick": 1,
    "byline": "Glenn Kenny",
    "headline": "‘Sr.’ Review: The Downeys, Father and Son, Compare Notes",
    "summary_short": "This documentary highlights Robert Downey Sr.’s charisma and curiosity even when it shows him in decline.",
    "publication_date": "2022-12-01",
    "opening_date": "2022-12-02",
    "date_updated": "2022-12-01 12:01:04",
    "link": {
        "type": "article",
        "url": "https://www.nytimes.com/2022/12/01/movies/sr-robert-downey-review.html",
        "suggested_link_text": "Read the New York Times Review of Sr."
    },
    "multimedia": {
        "type": "mediumThreeByTwo210",
        "src": "https://static01.nyt.com/images/2022/12/01/arts/01senior-review/01senior-review-mediumThreeByTwo440.jpg",
        "height": 140,
        "width": 210
    }
}, {
    "display_title": "Emancipation",
    "mpaa_rating": "R",
    "critics_pick": 0,
    "byline": "Manohla Dargis",
    "headline": "‘Emancipation’ Review: Will Smith in a Brutal Journey",
    "summary_short": "The actor stars in this Civil War-era drama directed by Antoine Fuqua and inspired by a shocking photograph of an enslaved man.",
    "publication_date": "2022-12-01",
    "opening_date": "2022-12-02",
    "date_updated": "2022-12-01 20:23:08",
    "link": {
        "type": "article",
        "url": "https://www.nytimes.com/2022/12/01/movies/emancipation-review-will-smith.html",
        "suggested_link_text": "Read the New York Times Review of Emancipation"
    },
    "multimedia": {
        "type": "mediumThreeByTwo210",
        "src": "https://static01.nyt.com/images/2022/12/01/multimedia/01emancipation-review-1-43a3/01emancipation-review-1-43a3-mediumThreeByTwo440.jpg",
        "height": 140,
        "width": 210
    }
}, {
    "display_title": "Four Samosas",
    "mpaa_rating": "PG-13",
    "critics_pick": 0,
    "byline": "Beatrice Loayza",
    "headline": "‘Four Samosas’ Review: A Romp Through Little India",
    "summary_short": "This snappy indie comedy by Ravi Kapoor sees a group of Indian American teenagers hatch a harebrained plan to steal a bag of diamonds.",
    "publication_date": "2022-12-01",
    "opening_date": "2022-12-02",
    "date_updated": "2022-12-01 18:29:03",
    "link": {
        "type": "article",
        "url": "https://www.nytimes.com/2022/12/01/movies/four-samosas-review.html",
        "suggested_link_text": "Read the New York Times Review of Four Samosas"
    },
    "multimedia": {
        "type": "mediumThreeByTwo210",
        "src": "https://static01.nyt.com/images/2022/12/01/multimedia/foursamosas1-1-f4ee/foursamosas1-1-f4ee-mediumThreeByTwo440-v2.jpg",
        "height": 140,
        "width": 210
    }
}, {
    "display_title": "Framing Agnes",
    "mpaa_rating": "",
    "critics_pick": 0,
    "byline": "Teo Bugbee",
    "headline": "‘Framing Agnes’ Review: Transition, Center Stage",
    "summary_short": "The documentarian Chase Joynt stages re-enactments of midcentury medical interviews with transgender people.",
    "publication_date": "2022-12-01",
    "opening_date": null,
    "date_updated": "2022-12-01 18:25:24",
    "link": {
        "type": "article",
        "url": "https://www.nytimes.com/2022/12/01/movies/framing-agnes-review.html",
        "suggested_link_text": "Read the New York Times Review of Framing Agnes"
    },
    "multimedia": {
        "type": "mediumThreeByTwo210",
        "src": "https://static01.nyt.com/images/2022/12/01/multimedia/framing1/framing1-1-f907-mediumThreeByTwo440.jpg",
        "height": 140,
        "width": 210
    }
}, {
    "display_title": "Darby and the Dead",
    "mpaa_rating": "PG-13",
    "critics_pick": 0,
    "byline": "Natalia Winkelman",
    "headline": "‘Darby and the Dead’ Review: Sixteen With a Sixth Sense",
    "summary_short": "A high school junior talks to dead people in this familiar but good-natured tale of adolescent female friendship.",
    "publication_date": "2022-12-01",
    "opening_date": "2022-12-02",
    "date_updated": "2022-12-01 18:22:10",
    "link": {
        "type": "article",
        "url": "https://www.nytimes.com/2022/12/01/movies/darby-and-the-dead-review.html",
        "suggested_link_text": "Read the New York Times Review of Darby and the Dead"
    },
    "multimedia": {
        "type": "mediumThreeByTwo210",
        "src": "https://static01.nyt.com/images/2022/12/01/multimedia/darby1/darby1-1-e91e-mediumThreeByTwo440.jpg",
        "height": 140,
        "width": 210
    }
}, {
    "display_title": "Lady Chatterley's Lover",
    "mpaa_rating": "R",
    "critics_pick": 0,
    "byline": "A.O. Scott",
    "headline": "‘Lady Chatterley’s Lover’ Review: When Connie Met Ollie",
    "summary_short": "The new Netflix adaptation of D.H. Lawrence’s once-controversial novel is both steamy and decorous.",
    "publication_date": "2022-12-01",
    "opening_date": "2022-12-02",
    "date_updated": "2022-12-01 16:41:03",
    "link": {
        "type": "article",
        "url": "https://www.nytimes.com/2022/12/01/movies/lady-chatterleys-lover-review.html",
        "suggested_link_text": "Read the New York Times Review of Lady Chatterley's Lover"
    },
    "multimedia": {
        "type": "mediumThreeByTwo210",
        "src": "https://static01.nyt.com/images/2022/12/01/multimedia/01ladychatterley-1-2403/01ladychatterley-1-2403-mediumThreeByTwo440.jpg",
        "height": 140,
        "width": 210
    }
}, {
    "display_title": "Farha",
    "mpaa_rating": "",
    "critics_pick": 0,
    "byline": "Beatrice Loayza",
    "headline": "‘Farha’ Review: A Most Brutal Coming-of-Age Story",
    "summary_short": "Set in the early days of the Israeli-Palestinian conflict, this drama depicts the upheaval of Palestinian society from a 14-year-old girl’s perspective.",
    "publication_date": "2022-12-01",
    "opening_date": null,
    "date_updated": "2022-12-01 16:32:03",
    "link": {
        "type": "article",
        "url": "https://www.nytimes.com/2022/12/01/movies/farha-review.html",
        "suggested_link_text": "Read the New York Times Review of Farha"
    },
    "multimedia": {
        "type": "mediumThreeByTwo210",
        "src": "https://static01.nyt.com/images/2022/12/01/multimedia/01farha-review-1-26c4/01farha-review-1-26c4-mediumThreeByTwo440.jpg",
        "height": 140,
        "width": 210
    }
}, {
    "display_title": "Scrooge: A Christmas Carol",
    "mpaa_rating": "TV-Y7",
    "critics_pick": 0,
    "byline": "Lisa Kennedy",
    "headline": "‘Scrooge: A Christmas Carol’ Review: Slightly Off Key",
    "summary_short": "Luke Evans, Olivia Colman and Jessie Buckley lend their voices to this animated musical of the holiday classic.",
    "publication_date": "2022-12-01",
    "opening_date": "2022-12-02",
    "date_updated": "2022-12-01 15:48:04",
    "link": {
        "type": "article",
        "url": "https://www.nytimes.com/2022/12/01/movies/scrooge-a-christmas-carol-review.html",
        "suggested_link_text": "Read the New York Times Review of Scrooge: A Christmas Carol"
    },
    "multimedia": {
        "type": "mediumThreeByTwo210",
        "src": "https://static01.nyt.com/images/2022/12/01/multimedia/christmascarol1/christmascarol1-1-f538-mediumThreeByTwo440.jpg",
        "height": 140,
        "width": 210
    }
}, {
    "display_title": "2nd Chance",
    "mpaa_rating": "",
    "critics_pick": 0,
    "byline": "Nicolas Rapold",
    "headline": "‘2nd Chance’ Review: Just Shoot Me",
    "summary_short": "Ramin Bahrani’s first documentary feature profiles Richard Davis, the irrepressible inventor of a modern bulletproof vest.",
    "publication_date": "2022-12-01",
    "opening_date": null,
    "date_updated": "2022-12-01 14:30:03",
    "link": {
        "type": "article",
        "url": "https://www.nytimes.com/2022/12/01/movies/2nd-chance-review.html",
        "suggested_link_text": "Read the New York Times Review of 2nd Chance"
    },
    "multimedia": {
        "type": "mediumThreeByTwo210",
        "src": "https://static01.nyt.com/images/2022/12/02/multimedia/second1-1-08b2/second1-1-08b2-mediumThreeByTwo440.jpg",
        "height": 140,
        "width": 210
    }
}, {
    "display_title": "Spoiler Alert",
    "mpaa_rating": "PG-13",
    "critics_pick": 0,
    "byline": "Amy Nicholson",
    "headline": "‘Spoiler Alert’ Review: Perfect Strangers Form Family Ties",
    "summary_short": "Jim Parsons and Ben Aldridge star in this tear-jerker romance adapted from the memoir by the television journalist Michael Ausiello.",
    "publication_date": "2022-12-01",
    "opening_date": "2022-12-09",
    "date_updated": "2022-12-01 14:27:03",
    "link": {
        "type": "article",
        "url": "https://www.nytimes.com/2022/12/01/movies/spoiler-alert-review.html",
        "suggested_link_text": "Read the New York Times Review of Spoiler Alert"
    },
    "multimedia": {
        "type": "mediumThreeByTwo210",
        "src": "https://static01.nyt.com/images/2022/12/01/multimedia/spoiler1-1-03bd/spoiler1-1-03bd-mediumThreeByTwo440.jpg",
        "height": 140,
        "width": 210
    }
}, {
    "display_title": "Violent Night",
    "mpaa_rating": "R",
    "critics_pick": 0,
    "byline": "Elisabeth Vincentelli",
    "headline": "‘Violent Night’ Review: Yucks, Not Yule",
    "summary_short": "Tommy Wirkola’s film tries to pass off sadism as comedy.",
    "publication_date": "2022-12-01",
    "opening_date": "2022-12-02",
    "date_updated": "2022-12-01 14:05:07",
    "link": {
        "type": "article",
        "url": "https://www.nytimes.com/2022/12/01/movies/violent-night-review.html",
        "suggested_link_text": "Read the New York Times Review of Violent Night"
    },
    "multimedia": {
        "type": "mediumThreeByTwo210",
        "src": "https://static01.nyt.com/images/2022/12/01/multimedia/violent1/violent1-1-c2ce-mediumThreeByTwo440.jpg",
        "height": 140,
        "width": 210
    }
}, {
    "display_title": "What Remains",
    "mpaa_rating": "",
    "critics_pick": 0,
    "byline": "Brandon Yu",
    "headline": "‘What Remains’ Review: Murder Thriller Without the Thrills",
    "summary_short": "This film about a small-town pastor hoping to mentor his wife’s killer includes one of the final performances from Anne Heche.",
    "publication_date": "2022-12-01",
    "opening_date": "2022-12-02",
    "date_updated": "2022-12-01 13:14:03",
    "link": {
        "type": "article",
        "url": "https://www.nytimes.com/2022/12/01/movies/what-remains-review.html",
        "suggested_link_text": "Read the New York Times Review of What Remains"
    },
    "multimedia": {
        "type": "mediumThreeByTwo210",
        "src": "https://static01.nyt.com/images/2022/12/01/multimedia/whatremains1/whatremains1-mediumThreeByTwo440.jpg",
        "height": 140,
        "width": 210
    }
}, {
    "display_title": "Hunt",
    "mpaa_rating": "",
    "critics_pick": 0,
    "byline": "Robert Daniels",
    "headline": "‘Hunt’ Review: Spy vs. Spy vs. Subplots",
    "summary_short": "A dense espionage narrative proves all too tangled in this directorial debut from the South Korean actor Lee Jung-jae.",
    "publication_date": "2022-12-01",
    "opening_date": "2022-12-02",
    "date_updated": "2022-12-01 12:02:04",
    "link": {
        "type": "article",
        "url": "https://www.nytimes.com/2022/12/01/movies/hunt-review.html",
        "suggested_link_text": "Read the New York Times Review of Hunt"
    },
    "multimedia": {
        "type": "mediumThreeByTwo210",
        "src": "https://static01.nyt.com/images/2022/12/01/multimedia/01hunt-review/01hunt-review-1-d185-mediumThreeByTwo440.jpg",
        "height": 140,
        "width": 210
    }
}, {
    "display_title": "Ainbo",
    "mpaa_rating": "TV-Y7",
    "critics_pick": 0,
    "byline": "Beandrea July",
    "headline": "‘Ainbo’ Review: Saved by a Princess",
    "summary_short": "The eponymous young huntress of this animated feature forges a plan to protect her village in the Amazon rainforest.",
    "publication_date": "2022-11-29",
    "opening_date": "2022-02-04",
    "date_updated": "2022-11-29 18:16:03",
    "link": {
        "type": "article",
        "url": "https://www.nytimes.com/2022/11/29/movies/ainbo-review.html",
        "suggested_link_text": "Read the New York Times Review of Ainbo"
    },
    "multimedia": {
        "type": "mediumThreeByTwo210",
        "src": "https://static01.nyt.com/images/2022/11/29/multimedia/29ainbo1-1-a876/29ainbo1-1-a876-mediumThreeByTwo440.jpg",
        "height": 140,
        "width": 210
    }
}, {
    "display_title": "The Noel Diary",
    "mpaa_rating": "TV-14",
    "critics_pick": 0,
    "byline": "Lisa Kennedy",
    "headline": "‘The Noel Diary’ Review: Revelations on a Cold Winter’s Night",
    "summary_short": "Justin Hartley (“This Is Us”) is no stranger to the themes in this holiday romance, while Barrett Doss (“Station 19”) brings nuanced comedic timing and charm.",
    "publication_date": "2022-11-24",
    "opening_date": "2022-11-24",
    "date_updated": "2022-11-29 17:36:32",
    "link": {
        "type": "article",
        "url": "https://www.nytimes.com/2022/11/24/movies/the-noel-diary-review.html",
        "suggested_link_text": "Read the New York Times Review of The Noel Diary"
    },
    "multimedia": {
        "type": "mediumThreeByTwo210",
        "src": "https://static01.nyt.com/images/2022/11/25/arts/24noeldiary-review1/24noeldiary-review1-mediumThreeByTwo440.jpg",
        "height": 140,
        "width": 210
    }
}]